livingmodels/__init__.py
livingmodels/base_model.py
livingmodels/estate_models.py
livingmodels/files_models.py
livingmodels/house_management_models.py
livingmodels/order_models.py
livingmodels/service_requests_models.py
livingmodels/services_guide_models.py
livingmodels-0.9.7.dist-info/METADATA
livingmodels-0.9.7.dist-info/WHEEL
livingmodels-0.9.7.dist-info/top_level.txt
livingmodels-0.9.7.dist-info/RECORD
