Metadata-Version: 2.1
Name: livingmodels
Version: 0.9.7
Summary: Models for global admin
Home-page: UNKNOWN
Author-email: 777koba@mail.ru
License: UNKNOWN
Platform: UNKNOWN
Requires-Dist: requests
Requires-Dist: SQLAlchemy (==1.4.39)
Requires-Dist: importlib-metadata ; python_version == "3.10"
